[{"text": "I\u2019ll be on @AC360 at 830pm ET w @VanJones68 talking Mueller news ... @cnn", "timestamp": "18:23 - 22. M\u00e4rz 2019", "retweet_count": "5", "favorite_count": "149", "author": "KirstenPowers", "is_retweet": true}, {"text": "", "timestamp": "12:38 - 21. M\u00e4rz 2019", "retweet_count": "2", "favorite_count": "40", "author": "KirstenPowers", "is_retweet": true}, {"text": "preach sis ", "timestamp": "06:59 - 21. M\u00e4rz 2019", "retweet_count": "1", "favorite_count": "34", "author": "KirstenPowers", "is_retweet": true}, {"text": "Def needs to be on your resume", "timestamp": "06:56 - 21. M\u00e4rz 2019", "retweet_count": "2", "favorite_count": "167", "author": "KirstenPowers", "is_retweet": true}, {"text": "@yashar", "timestamp": "14:13 - 19. M\u00e4rz 2019", "retweet_count": "0", "favorite_count": "5", "author": "KirstenPowers", "is_retweet": true}, {"text": "Yes! Just signed on to support this. Everyone check out my friend  @austinchanning\u2019s show focused on moving the conversation on race forward.  I love her vision.  #teamaustinchanningbrown", "timestamp": "18:03 - 18. M\u00e4rz 2019", "retweet_count": "1", "favorite_count": "21", "author": "KirstenPowers", "is_retweet": true}, {"text": "Good morning! I\u2019ll be on @NewDay at 8am this morning ... @cnn", "timestamp": "04:46 - 18. M\u00e4rz 2019", "retweet_count": "2", "favorite_count": "149", "author": "KirstenPowers", "is_retweet": true}, {"text": "Ill be on @AC360 with @MaxBoot coming up ... @cnn", "timestamp": "17:19 - 15. M\u00e4rz 2019", "retweet_count": "2", "favorite_count": "117", "author": "KirstenPowers", "is_retweet": true}, {"text": "I\u2019ll be on @AC360 coming up ... lots to talk about ... @cnn", "timestamp": "16:57 - 14. M\u00e4rz 2019", "retweet_count": "7", "favorite_count": "177", "author": "KirstenPowers", "is_retweet": true}, {"text": "Thank you for the best show out there! Our house is in countdown mode for new season ...", "timestamp": "17:38 - 13. M\u00e4rz 2019", "retweet_count": "0", "favorite_count": "13", "author": "KirstenPowers", "is_retweet": true}, {"text": "Oh I know!! ", "timestamp": "17:34 - 13. M\u00e4rz 2019", "retweet_count": "0", "favorite_count": "2", "author": "KirstenPowers", "is_retweet": true}, {"text": "I\u2019ll be on @AC360 coming up ...@cnn", "timestamp": "17:04 - 13. M\u00e4rz 2019", "retweet_count": "3", "favorite_count": "259", "author": "KirstenPowers", "is_retweet": true}, {"text": "I\u2019ll be on @CNNTonight coming up after the break ... @CNN", "timestamp": "19:52 - 11. M\u00e4rz 2019", "retweet_count": "6", "favorite_count": "250", "author": "KirstenPowers", "is_retweet": true}, {"text": "I\u2019ll be on @AC360 with @angela_rye coming up to discuss @SpeakerPelosi comments on impeachment....@CNN", "timestamp": "17:18 - 11. M\u00e4rz 2019", "retweet_count": "9", "favorite_count": "153", "author": "KirstenPowers", "is_retweet": true}, {"text": "While RW publications have misrepresented my comments (shock!) this was the point I was making on @cnn \n\u201cThe point is not to excuse Omar by comparison. It\u2019s to say that Omar said things that are offensive and that she\u2019s the victim of a double standard.\u201d", "timestamp": "14:51 - 8. M\u00e4rz 2019", "retweet_count": "31", "favorite_count": "224", "author": "KirstenPowers", "is_retweet": true}, {"text": "Coming up I\u2019ll be on @AC360 ... @cnn", "timestamp": "17:33 - 7. M\u00e4rz 2019", "retweet_count": "7", "favorite_count": "170", "author": "KirstenPowers", "is_retweet": true}, {"text": "From my appearance on @TheLeadCNN today \n\nTrump-defender left speechless after CNN analyst reads anti-Semitic Trump quote over his objections \n\nhttps://www.rawstory.com/?p=1460267  via @RawStory", "timestamp": "15:08 - 7. M\u00e4rz 2019", "retweet_count": "195", "favorite_count": "929", "author": "KirstenPowers", "is_retweet": true}, {"text": "I\u2019ll be on @TheLeadCNN coming up w my longtime pal @JamalSimmons (he has stories!) to talk Manafort, Biden run and Dem \u201canti-hate\u201d resolution... @CNN", "timestamp": "13:06 - 7. M\u00e4rz 2019", "retweet_count": "11", "favorite_count": "157", "author": "KirstenPowers", "is_retweet": true}, {"text": "Rise and shine sleepyheads! I\u2019ll be on @NewDay coming up .... @cnn", "timestamp": "03:02 - 7. M\u00e4rz 2019", "retweet_count": "10", "favorite_count": "322", "author": "KirstenPowers", "is_retweet": true}, {"text": "How have u never been on @Jeopardy? You were made for that.", "timestamp": "17:34 - 6. M\u00e4rz 2019", "retweet_count": "3", "favorite_count": "43", "author": "KirstenPowers", "is_retweet": true}, {"text": "I\u2019ll be on @AC360 coming up discussing the @DNC decision to not have Dem #2020 candidates participate in a @FoxNews debate ... @CNN", "timestamp": "17:18 - 6. M\u00e4rz 2019", "retweet_count": "21", "favorite_count": "359", "author": "KirstenPowers", "is_retweet": true}, {"text": "I hope we get to be on together ", "timestamp": "14:34 - 6. M\u00e4rz 2019", "retweet_count": "2", "favorite_count": "18", "author": "KirstenPowers", "is_retweet": true}, {"text": "Meet the teenagers who started a feminist club at their all-boys Catholic prep school. \n\n\u201cThey have hosted standing-room-only meetings during their lunch period, offering free pizza to draw crowds of upward of 40 boys.\u201d  ", "timestamp": "05:53 - 6. M\u00e4rz 2019", "retweet_count": "45", "favorite_count": "346", "author": "KirstenPowers", "is_retweet": true}, {"text": "I\u2019ll be on @AC360 coming up ... lots to talk about! @cnn", "timestamp": "17:00 - 5. M\u00e4rz 2019", "retweet_count": "8", "favorite_count": "321", "author": "KirstenPowers", "is_retweet": true}, {"text": "Today, on #DayOfEmpathy, Ellie and I stand in solidarity with @cut_50 & criminal justice reform advocates across the country to build empathy for the millions affected by mass incarceration. Crime hurts, but justice should heal. Join the movement: http://DayOfEmpathy.org . Pls RT!", "timestamp": "08:38 - 5. M\u00e4rz 2019", "retweet_count": "72", "favorite_count": "249", "author": "KirstenPowers", "is_retweet": true}, {"text": "Check out this interview with my friend @emerzian on @TODAYshow this morning about his amazing book #EveryMondayMatters.  So inspiring!", "timestamp": "13:38 - 4. M\u00e4rz 2019", "retweet_count": "4", "favorite_count": "30", "author": "KirstenPowers", "is_retweet": true}, {"text": "I\u2019ll be on @AC360 coming up with @MaxBoot ... @CNN", "timestamp": "17:01 - 1. M\u00e4rz 2019", "retweet_count": "7", "favorite_count": "222", "author": "KirstenPowers", "is_retweet": true}, {"text": "Ill be on @AC360 coming up ...@CNN", "timestamp": "16:59 - 28. Feb. 2019", "retweet_count": "5", "favorite_count": "329", "author": "KirstenPowers", "is_retweet": true}, {"text": "I\u2019ll be on @AC360 coming up to discuss the Cohen hearing today @CNN", "timestamp": "17:12 - 27. Feb. 2019", "retweet_count": "17", "favorite_count": "527", "author": "KirstenPowers", "is_retweet": true}, {"text": "Thanks sister ", "timestamp": "17:44 - 20. Feb. 2019", "retweet_count": "1", "favorite_count": "17", "author": "KirstenPowers", "is_retweet": true}, {"text": "Is this too much to hope for? Read @matthewjdowd...\n\n2020 presidential races: Running a 'conscious campaign' - ABC News -  via @ABC", "timestamp": "13:05 - 20. Feb. 2019", "retweet_count": "6", "favorite_count": "46", "author": "KirstenPowers", "is_retweet": true}, {"text": "it's called being on a spiritual path...and working to integrate my beliefs into my life, .... has nothing to do with chasing anything or slaying demons lol", "timestamp": "09:36 - 20. Feb. 2019", "retweet_count": "0", "favorite_count": "3", "author": "KirstenPowers", "is_retweet": true}, {"text": "In my quest to be more mindful of the importance of grace, I started this last night and am already half way through it.  \n\nGood stuff.", "timestamp": "09:27 - 20. Feb. 2019", "retweet_count": "49", "favorite_count": "730", "author": "KirstenPowers", "is_retweet": true}, {"text": "thanks friend...miss you!", "timestamp": "09:02 - 20. Feb. 2019", "retweet_count": "0", "favorite_count": "1", "author": "KirstenPowers", "is_retweet": true}, {"text": "", "timestamp": "08:36 - 20. Feb. 2019", "retweet_count": "0", "favorite_count": "3", "author": "KirstenPowers", "is_retweet": true}, {"text": "No it isnt. That wasn\u2019t remotely my point", "timestamp": "07:00 - 20. Feb. 2019", "retweet_count": "0", "favorite_count": "18", "author": "KirstenPowers", "is_retweet": true}, {"text": "Yes, as all my friends know, I am constantly wrestling with how to do this, esp the not judging or loving your enemies part.  It\u2019s easy to say you believe these things, but harder to live them out amidst such toxicity and divisiveness.  Tho I\u2019m determined to figure it out.", "timestamp": "06:35 - 20. Feb. 2019", "retweet_count": "36", "favorite_count": "749", "author": "KirstenPowers", "is_retweet": true}, {"text": "It actually wasn\u2019t an interview request.  about a week ago i reached out to see if I could meet up with them and their families to express my own regrets and also to express my commitment to helping ensure this one incident doesn\u2019t define them, bc that was never my goal.", "timestamp": "05:55 - 20. Feb. 2019", "retweet_count": "0", "favorite_count": "7", "author": "KirstenPowers", "is_retweet": true}, {"text": "@Julie_rodgers", "timestamp": "19:31 - 19. Feb. 2019", "retweet_count": "0", "favorite_count": "4", "author": "KirstenPowers", "is_retweet": true}, {"text": "", "timestamp": "18:19 - 19. Feb. 2019", "retweet_count": "1", "favorite_count": "48", "author": "KirstenPowers", "is_retweet": true}, {"text": "no i'll check it out!", "timestamp": "14:42 - 19. Feb. 2019", "retweet_count": "0", "favorite_count": "2", "author": "KirstenPowers", "is_retweet": true}, {"text": "8holes ", "timestamp": "14:21 - 19. Feb. 2019", "retweet_count": "0", "favorite_count": "2", "author": "KirstenPowers", "is_retweet": true}, {"text": "I hear you", "timestamp": "14:16 - 19. Feb. 2019", "retweet_count": "0", "favorite_count": "9", "author": "KirstenPowers", "is_retweet": true}, {"text": "you have NO idea how much my work with the enneagram contributed to me seeing all of my behavior differently", "timestamp": "13:24 - 19. Feb. 2019", "retweet_count": "0", "favorite_count": "13", "author": "KirstenPowers", "is_retweet": true}, {"text": "yeah i wrote a column to publicize a column.  you've figure out my game lol", "timestamp": "13:12 - 19. Feb. 2019", "retweet_count": "0", "favorite_count": "31", "author": "KirstenPowers", "is_retweet": true}, {"text": "let's find out :-)", "timestamp": "13:02 - 19. Feb. 2019", "retweet_count": "1", "favorite_count": "6", "author": "KirstenPowers", "is_retweet": true}, {"text": "Here is my @usatoday column expanding on my Twitter thread yesterday. \n\n\"I'm not proud of role I\u2019ve played in toxic public debate. I plan to change.\" https://www.usatoday.com/story/opinion/2019/02/19/kirsten-powers-covington-apology-twitter-franken-social-media-toxic-column/2915856002/ \u2026 via @usatoday", "timestamp": "12:54 - 19. Feb. 2019", "retweet_count": "139", "favorite_count": "706", "author": "KirstenPowers", "is_retweet": true}, {"text": "I'm not going to stop talking about them...don't worry!", "timestamp": "12:30 - 19. Feb. 2019", "retweet_count": "0", "favorite_count": "3", "author": "KirstenPowers", "is_retweet": true}, {"text": "Good for you!", "timestamp": "09:52 - 19. Feb. 2019", "retweet_count": "0", "favorite_count": "1", "author": "KirstenPowers", "is_retweet": true}, {"text": "Love u bob ", "timestamp": "09:49 - 19. Feb. 2019", "retweet_count": "0", "favorite_count": "10", "author": "KirstenPowers", "is_retweet": true}, {"text": "I actually did and they weren\u2019t interested, dear.", "timestamp": "09:48 - 19. Feb. 2019", "retweet_count": "19", "favorite_count": "468", "author": "KirstenPowers", "is_retweet": true}, {"text": "Then why are u following me?", "timestamp": "09:44 - 19. Feb. 2019", "retweet_count": "0", "favorite_count": "2", "author": "KirstenPowers", "is_retweet": true}, {"text": "This is exactly what is wrong w social media.  I was saying what I thought at the time it was unfolding. I was making a broader point abt how ppl end up getting punishments that don\u2019t fit the crime bc of social media.  But you know that.", "timestamp": "05:49 - 19. Feb. 2019", "retweet_count": "3", "favorite_count": "145", "author": "KirstenPowers", "is_retweet": true}, {"text": "I\u2019ll be discussing our toxic culture and my role in it, per this thread, on @NewDay around 830am ET.. @CNN", "timestamp": "04:51 - 19. Feb. 2019", "retweet_count": "23", "favorite_count": "320", "author": "KirstenPowers", "is_retweet": true}, {"text": "Ty friend ", "timestamp": "04:05 - 19. Feb. 2019", "retweet_count": "1", "favorite_count": "11", "author": "KirstenPowers", "is_retweet": true}, {"text": "I\u2019ll be back on @AC360 with @brianefallon talking 2020 and upcoming @amyklobuchar town hall on @CNN ... coming up", "timestamp": "18:47 - 18. Feb. 2019", "retweet_count": "10", "favorite_count": "188", "author": "KirstenPowers", "is_retweet": true}, {"text": "Ill be on @AC360 coming up to discuss McCabe revelations @cnn", "timestamp": "17:26 - 18. Feb. 2019", "retweet_count": "7", "favorite_count": "216", "author": "KirstenPowers", "is_retweet": true}, {"text": "And actually studying the enneagram is exactly what helped me see my behavior and why I was doing it", "timestamp": "17:22 - 18. Feb. 2019", "retweet_count": "0", "favorite_count": "3", "author": "KirstenPowers", "is_retweet": true}, {"text": "No I\u2019m not but good guess", "timestamp": "17:22 - 18. Feb. 2019", "retweet_count": "0", "favorite_count": "6", "author": "KirstenPowers", "is_retweet": true}, {"text": "Really appreciate @MJGerson talk at @WNCathedral yesterday where he gets real about depression, including his own hospitalization for the disease.  Watch it for encouragement if you need it.", "timestamp": "14:52 - 18. Feb. 2019", "retweet_count": "8", "favorite_count": "111", "author": "KirstenPowers", "is_retweet": true}, {"text": "I love that idea!", "timestamp": "11:57 - 18. Feb. 2019", "retweet_count": "1", "favorite_count": "3", "author": "KirstenPowers", "is_retweet": true}, {"text": "TY -- love Russell Brand...will check it out.", "timestamp": "11:05 - 18. Feb. 2019", "retweet_count": "0", "favorite_count": "7", "author": "KirstenPowers", "is_retweet": true}, {"text": "That's right -- there is a fine line.  And I want to do my best to stay on the right side of that line. And yes: people are better than their worst moments in life.", "timestamp": "11:03 - 18. Feb. 2019", "retweet_count": "14", "favorite_count": "134", "author": "KirstenPowers", "is_retweet": true}, {"text": "", "timestamp": "11:00 - 18. Feb. 2019", "retweet_count": "0", "favorite_count": "12", "author": "KirstenPowers", "is_retweet": true}, {"text": "thank you -- i don't plan on changing that.  I am more interested in working on the \"judgy\" part that comes out mostly on Twitter and my columns, but can seep into commentary from time to time", "timestamp": "10:34 - 18. Feb. 2019", "retweet_count": "1", "favorite_count": "4", "author": "KirstenPowers", "is_retweet": true}, {"text": "TY but i know i can do better than what i've done, esp here on Twitter.  There is a way to stand up for what you believe without rushing to judgment ... and that includes even after all the facts are in. there is something to be said for taking time to think about an issue...", "timestamp": "10:30 - 18. Feb. 2019", "retweet_count": "1", "favorite_count": "5", "author": "KirstenPowers", "is_retweet": true}, {"text": "There is a way to hold people accountable and not be judgmental. Also i really do believe people are not the sum of their worst moments in life and too often in the media we make it seem like they are.", "timestamp": "10:21 - 18. Feb. 2019", "retweet_count": "28", "favorite_count": "787", "author": "KirstenPowers", "is_retweet": true}, {"text": "yes that's the challenge ... but if I can't figure out a way to do this in a way that is consistent with who I want to be then I'll have to find another career....", "timestamp": "10:14 - 18. Feb. 2019", "retweet_count": "3", "favorite_count": "145", "author": "KirstenPowers", "is_retweet": true}, {"text": "exactly! i've worked so hard to not be a hypocrite but then became someone sitting in judgement in every situation to try and stay consistent....just as bad.", "timestamp": "10:04 - 18. Feb. 2019", "retweet_count": "0", "favorite_count": "6", "author": "KirstenPowers", "is_retweet": true}, {"text": "8)  I also hope to be part of a conversation -- if we ever have it as a country -- about the path to redemption for people who have stumbled and even failed spectacularly.  This is where I plan to put my focus and not on rendering judgements about other people's behavior. THE END", "timestamp": "09:58 - 18. Feb. 2019", "retweet_count": "194", "favorite_count": "5789", "author": "KirstenPowers", "is_retweet": true}, {"text": "7) I often am too rigid in trying to be pure in my principles and don't leave enough room for this mess of life.  So I'm writing this as an apology to both left and right and making a pledge to do better.", "timestamp": "09:56 - 18. Feb. 2019", "retweet_count": "102", "favorite_count": "2299", "author": "KirstenPowers", "is_retweet": true}, {"text": "6) It should be said I have been an equal opportunity scold, and liberals have been on the receiving end of my judgement and I regret that as well. I am rethinking my view on Al Franken, for example, after hearing from many friends on the issue of the rush to judgement.", "timestamp": "09:54 - 18. Feb. 2019", "retweet_count": "75", "favorite_count": "1451", "author": "KirstenPowers", "is_retweet": true}, {"text": "5) I also don't believe these teenagers should be tarnished forever for what amounts to one really bad day. I know that black teenage boys don't get this benefit of the doubt or grace, but I want more black teenage boys to get this benefit, not fewer white teenage boys.", "timestamp": "09:51 - 18. Feb. 2019", "retweet_count": "102", "favorite_count": "2516", "author": "KirstenPowers", "is_retweet": true}, {"text": "4)  Yes, this applies in the Covington case. This will please nobody because I still believe the teenagers were disrespectful, but my tweets were lacking in grace. As a Catholic I felt duty bound to speak up and hold them accountable, but that really isn't my job.", "timestamp": "09:49 - 18. Feb. 2019", "retweet_count": "84", "favorite_count": "1719", "author": "KirstenPowers", "is_retweet": true}, {"text": "3) I want to stand on the side of justice and equality but also of grace and I have failed to do that. Part of grace is recognizing my own fallibilities and imperfect judgment and reminding myself that there but for the grace of God go I.", "timestamp": "09:43 - 18. Feb. 2019", "retweet_count": "113", "favorite_count": "2462", "author": "KirstenPowers", "is_retweet": true}, {"text": "2) I work hard to see\nevery side of an issue and also speak up when I see a wrong.  But in\ndoing that I am too often judgmental and condemning--both on and off social media--in a way that is\ncontrary to my belief system and my faith.", "timestamp": "09:39 - 18. Feb. 2019", "retweet_count": "90", "favorite_count": "2017", "author": "KirstenPowers", "is_retweet": true}, {"text": "1) I have spent the last few weeks in a mostly Twitter free zone to spend time reflecting on what role I may have played in what indisputably has become a dangerously toxic culture.  I am not proud of what I have found.", "timestamp": "09:38 - 18. Feb. 2019", "retweet_count": "1076", "favorite_count": "8616", "author": "KirstenPowers", "is_retweet": true}, {"text": "I\u2019ll be on @AC360 coming up discussing Trump\u2019s national emergency @CNN", "timestamp": "17:29 - 15. Feb. 2019", "retweet_count": "13", "favorite_count": "256", "author": "KirstenPowers", "is_retweet": true}, {"text": "Feeling is mutual!", "timestamp": "07:18 - 15. Feb. 2019", "retweet_count": "0", "favorite_count": "28", "author": "KirstenPowers", "is_retweet": true}, {"text": "I\u2019ll be on @AC360 coming up with @MaxBoot discussing Trump\u2019s threat to declare a national emergency", "timestamp": "17:30 - 14. Feb. 2019", "retweet_count": "6", "favorite_count": "150", "author": "KirstenPowers", "is_retweet": true}, {"text": "I think there is supposed to be a comma between faith and trauma though tbh it works without the comma too ;-)", "timestamp": "10:27 - 14. Feb. 2019", "retweet_count": "12", "favorite_count": "318", "author": "KirstenPowers", "is_retweet": true}, {"text": "Coming up I\u2019ll be on @AC360 ... @CNN", "timestamp": "17:36 - 13. Feb. 2019", "retweet_count": "6", "favorite_count": "227", "author": "KirstenPowers", "is_retweet": true}, {"text": "", "timestamp": "17:36 - 13. Feb. 2019", "retweet_count": "1", "favorite_count": "70", "author": "KirstenPowers", "is_retweet": true}, {"text": "Coming up I\u2019ll be on @AC360 with @CharlesMBlow discussing Virginia news, which keeps getting worse", "timestamp": "17:17 - 6. Feb. 2019", "retweet_count": "18", "favorite_count": "361", "author": "KirstenPowers", "is_retweet": true}, {"text": "Every day I get up and say \u201cno more Twitter\u201d and somehow end up back here.  I always regret it. \n\nDeleting the app now.", "timestamp": "10:36 - 23. Jan. 2019", "retweet_count": "508", "favorite_count": "7258", "author": "KirstenPowers", "is_retweet": true}, {"text": "So it\u2019s confirmation bias for me but not for you right? Anyone who disagrees with you has confirmation bias and anyone who agrees with you doesn\u2019t. Maybe come up with a new hot take.", "timestamp": "14:59 - 22. Jan. 2019", "retweet_count": "0", "favorite_count": "64", "author": "KirstenPowers", "is_retweet": true}, {"text": "love you sister", "timestamp": "10:29 - 22. Jan. 2019", "retweet_count": "2", "favorite_count": "72", "author": "KirstenPowers", "is_retweet": true}, {"text": "i know i'm sorry -- it's always a tough call...do i share and unleash the trolls or not? lmk if it's better to not share.  Fwiw, most of the nutty responses are from paid trolls or bots....i try to ignore them or block them when i have time.", "timestamp": "10:16 - 22. Jan. 2019", "retweet_count": "0", "favorite_count": "11", "author": "KirstenPowers", "is_retweet": true}, {"text": "shared!", "timestamp": "10:14 - 22. Jan. 2019", "retweet_count": "6", "favorite_count": "37", "author": "KirstenPowers", "is_retweet": true}, {"text": "\"The view that excessive income concentration corrodes the social contract has deep roots in America \u2014 a country founded, in part, in reaction against the highly unequal, aristocratic Europe of the 18th century.\"", "timestamp": "07:28 - 22. Jan. 2019", "retweet_count": "38", "favorite_count": "242", "author": "KirstenPowers", "is_retweet": true}, {"text": "It's about damn time.  Spike Lee is a national treasure.", "timestamp": "07:20 - 22. Jan. 2019", "retweet_count": "256", "favorite_count": "1734", "author": "KirstenPowers", "is_retweet": true}, {"text": "Coming up I\u2019ll be on @AC360 talking 2020 with @VanJones68 ... @CNN", "timestamp": "17:49 - 21. Jan. 2019", "retweet_count": "6", "favorite_count": "210", "author": "KirstenPowers", "is_retweet": true}, {"text": ".@CharlesMBlow is so righteous on @CNN right now.  I\u2019m just sorry  he has to spend his time educating people about basic racism.", "timestamp": "17:44 - 21. Jan. 2019", "retweet_count": "276", "favorite_count": "2554", "author": "KirstenPowers", "is_retweet": true}, {"text": "You did it again! you think that it's okay to harass an elderly man b/c you have been harassed.", "timestamp": "06:31 - 21. Jan. 2019", "retweet_count": "2", "favorite_count": "36", "author": "KirstenPowers", "is_retweet": true}, {"text": "Anyway, I'm done arguing about this.  I know what i see on that video and the school was right to apologize.  That's my take.", "timestamp": "06:30 - 21. Jan. 2019", "retweet_count": "0", "favorite_count": "15", "author": "KirstenPowers", "is_retweet": true}, {"text": "i didnt say they uttered it i said they referenced it by holding up fingers", "timestamp": "06:27 - 21. Jan. 2019", "retweet_count": "5", "favorite_count": "63", "author": "KirstenPowers", "is_retweet": true}, {"text": "you aren't saying that you actually can make out the words of all the chants are you?  I don't think you are -- in which case you don't know.  So stop suggesting that you not hearing it in the video is dispositive of something.", "timestamp": "06:24 - 21. Jan. 2019", "retweet_count": "0", "favorite_count": "30", "author": "KirstenPowers", "is_retweet": true}, {"text": "is that what you call referencing a black classmate as  N-----?  \"not reacting perfectly?\"", "timestamp": "06:23 - 21. Jan. 2019", "retweet_count": "8", "favorite_count": "180", "author": "KirstenPowers", "is_retweet": true}, {"text": "\"There were also black men who identified themselves as Hebrew Israelites, preaching their beliefs and shouting racially combative comments at the Native Americans and the students, according to witnesses and video on social media.\"", "timestamp": "05:48 - 21. Jan. 2019", "retweet_count": "0", "favorite_count": "6", "author": "KirstenPowers", "is_retweet": true}, {"text": "This year, let's not do the annual American ritual of (literally) whitewashing MLK, Jr. into someone who makes white people feel good about themselves.\n\nOn #MLKDay read this by @michaelharriot in @theroot\n \nhttps://www.theroot.com/martin-luther-king-jr-and-the-white-delusion-of-a-non-1831910328?utm_medium=sharefromsite&utm_source=theroot_twitter&utm_campaign=top \u2026 \n\n#MartinLutherKingJrDay", "timestamp": "04:59 - 21. Jan. 2019", "retweet_count": "50", "favorite_count": "175", "author": "KirstenPowers", "is_retweet": true}, {"text": "\"I have almost reached the regrettable conclusion that the Negro\u2019s great stumbling block in his stride toward freedom is not the White Citizen\u2019s Counciler or the Ku Klux Klanner, but the white moderate, who is more devoted to 'order' than to justice.\" #MLK", "timestamp": "04:34 - 21. Jan. 2019", "retweet_count": "676", "favorite_count": "2661", "author": "KirstenPowers", "is_retweet": true}, {"text": "Two things\u20141. SCOTUS unanimously struck down that law, meaning the liberals saw it as a problem. 2. USCCB is conservative. I don\u2019t agree w everything they do...If there\u2019s a way to do a constitutional buffer zone and then I would totally support it", "timestamp": "13:16 - 19. Jan. 2019", "retweet_count": "2", "favorite_count": "11", "author": "KirstenPowers", "is_retweet": true}, {"text": "2/2 tho in the end she has a right to not like the Catholic Church...half the time i don't either.", "timestamp": "11:35 - 19. Jan. 2019", "retweet_count": "1", "favorite_count": "3", "author": "KirstenPowers", "is_retweet": true}, {"text": "1/2 Chris i don't think it's fair to expect her to be an expert. She's right that there are some basic things that are obvious (such as barring women from leadership).  I actually think it's incumbent on non-conservative catholics to try and explain the Church....", "timestamp": "11:34 - 19. Jan. 2019", "retweet_count": "1", "favorite_count": "2", "author": "KirstenPowers", "is_retweet": true}, {"text": "ok i've got to get off twitter!", "timestamp": "11:20 - 19. Jan. 2019", "retweet_count": "0", "favorite_count": "4", "author": "KirstenPowers", "is_retweet": true}, {"text": "I hear everything you say (it's like you were listening in on my spiritual direction session yesterday with @JamesMartinSJ lol).  I just don't' want you to buy into the conservative line about what the Bible says. That's all that gets attention in the media even tho it's so wrong", "timestamp": "11:20 - 19. Jan. 2019", "retweet_count": "0", "favorite_count": "4", "author": "KirstenPowers", "is_retweet": true}, {"text": "yes the institution is deeply flawed and it's flawed b/c of human (male imo) behavior. I agree the Bishops should speak up about this issue and misogyny in particular and i've told them that.", "timestamp": "11:18 - 19. Jan. 2019", "retweet_count": "2", "favorite_count": "9", "author": "KirstenPowers", "is_retweet": true}, {"text": "delete what? i never named the boy.", "timestamp": "11:15 - 19. Jan. 2019", "retweet_count": "0", "favorite_count": "2", "author": "KirstenPowers", "is_retweet": true}, {"text": "\"actual' not \"actually\"", "timestamp": "11:14 - 19. Jan. 2019", "retweet_count": "1", "favorite_count": "1", "author": "KirstenPowers", "is_retweet": true}, {"text": "2/ and not succumb to the idea that they have it right b/c what they have is flawed and it's flawed in large part b/c it's an all male institution that has been too committed to protecting the institution and male power", "timestamp": "11:14 - 19. Jan. 2019", "retweet_count": "1", "favorite_count": "6", "author": "KirstenPowers", "is_retweet": true}, {"text": "1/Well they are upheld by some people...but there are other people who are standing against that. You won't get any disagreement from me about the problem of the patriarchy esp in the Church.  The best way to do that is by holding them to the actually teaching of Jesus ....", "timestamp": "11:13 - 19. Jan. 2019", "retweet_count": "1", "favorite_count": "4", "author": "KirstenPowers", "is_retweet": true}, {"text": "also -- it's really hard to understand Catholic teaching if you only pay attention to the people in the political sphere who have weaponized it to support their views. it's much more nuanced and there is a constant push and pull btwn different views in the church.", "timestamp": "11:09 - 19. Jan. 2019", "retweet_count": "0", "favorite_count": "1", "author": "KirstenPowers", "is_retweet": true}, {"text": "I'm not really following your point..is it that if you go to a Catholic School that is anti-abortion rights that you will act in a racist way toward an elder?  Also many faithful Catholics (incl me) don't support overturning Roe v Wade.", "timestamp": "11:08 - 19. Jan. 2019", "retweet_count": "3", "favorite_count": "10", "author": "KirstenPowers", "is_retweet": true}, {"text": "Actually there is nothing in the Catholic teaching that says you should harass women at abortion clinics. You are basically buying what a subsection of conservatives claim Catholicism teaches instead of what it actually teaches.", "timestamp": "10:56 - 19. Jan. 2019", "retweet_count": "24", "favorite_count": "225", "author": "KirstenPowers", "is_retweet": true}, {"text": "I\u2019ll be on @AC360 with @MaxBoot coming up on @CNN", "timestamp": "17:38 - 17. Jan. 2019", "retweet_count": "15", "favorite_count": "346", "author": "KirstenPowers", "is_retweet": true}, {"text": "Wow this is deranged.  Can't say I'm surprised....here is something you might enjoy from the wayback machine of Jesse Lee Peterson", "timestamp": "15:52 - 17. Jan. 2019", "retweet_count": "16", "favorite_count": "158", "author": "KirstenPowers", "is_retweet": true}, {"text": "This has become my new favorite podcast.  Check out part one of my interview with @iancron.", "timestamp": "10:32 - 17. Jan. 2019", "retweet_count": "2", "favorite_count": "35", "author": "KirstenPowers", "is_retweet": true}, {"text": "@iancron is the correct handle!", "timestamp": "09:45 - 17. Jan. 2019", "retweet_count": "0", "favorite_count": "4", "author": "KirstenPowers", "is_retweet": true}, {"text": "And paid the firm \"$12,000 to $13,000 in cash in a plastic bag during a meeting at Trump Tower.\"\n\nTotally normal behavior.", "timestamp": "09:44 - 17. Jan. 2019", "retweet_count": "432", "favorite_count": "1594", "author": "KirstenPowers", "is_retweet": true}, {"text": "If you don't know about the Enneagram you should learn about it!  It has changed my life.  I got to dive into it with my friend @IanMorganCron on my new favorite podcast, the @TypologyPodcast! Give it a listen:", "timestamp": "09:35 - 17. Jan. 2019", "retweet_count": "5", "favorite_count": "32", "author": "KirstenPowers", "is_retweet": true}, {"text": "Great advice from @KamalaHarris for women: 'Don\u2019t let anybody tell you who you are, you tell them who you are.'  https://gma.abc/2AJTBlR  via @ABC\n\nPeople love to create stories about women, especially powerful women, that have nothing to do with who they really are.", "timestamp": "09:32 - 17. Jan. 2019", "retweet_count": "105", "favorite_count": "487", "author": "KirstenPowers", "is_retweet": true}, {"text": "My @usatoday column today:  Gillette commercial controversy: Men should just get over it and adapt to #MeToo era https://www.usatoday.com/story/opinion/2019/01/17/gillette-commercial-child-labor-sales-drop-masculinity-offensive-male-column/2602316002/ \u2026 via @usatopinon", "timestamp": "08:42 - 17. Jan. 2019", "retweet_count": "44", "favorite_count": "286", "author": "KirstenPowers", "is_retweet": true}, {"text": "I love that you did it year after year even after losing.  #NeverGiveUp", "timestamp": "17:45 - 16. Jan. 2019", "retweet_count": "3", "favorite_count": "63", "author": "KirstenPowers", "is_retweet": true}, {"text": "Coming up I\u2019ll be on @AC360 with all sorts of great ppl.... @cnn", "timestamp": "17:00 - 16. Jan. 2019", "retweet_count": "24", "favorite_count": "468", "author": "KirstenPowers", "is_retweet": true}, {"text": "\u201cCNN's Kirsten Powers asked critics of the @Gillette ad targetting 'toxic masculinity' why they find it so \u2018triggering\u2019and what is it about \"treating women with respect and equality that's so offensive to you?\u2019\u201d", "timestamp": "06:44 - 16. Jan. 2019", "retweet_count": "123", "favorite_count": "918", "author": "KirstenPowers", "is_retweet": true}, {"text": "Both\u2014which is why people who care about an independent DOJ should be suspicious.", "timestamp": "15:08 - 15. Jan. 2019", "retweet_count": "65", "favorite_count": "404", "author": "KirstenPowers", "is_retweet": true}, {"text": "I\u2019ll be on @AC360 coming up ....\n@CNN", "timestamp": "17:30 - 14. Jan. 2019", "retweet_count": "12", "favorite_count": "472", "author": "KirstenPowers", "is_retweet": true}, {"text": "Ill be on with @BrookeBCNN after the break talking Tulsi Gabbard and Steve King and more with @ananavarro @CNN", "timestamp": "12:27 - 14. Jan. 2019", "retweet_count": "5", "favorite_count": "210", "author": "KirstenPowers", "is_retweet": true}, {"text": "no need to feel terrible! it happens :-)", "timestamp": "02:19 - 14. Jan. 2019", "retweet_count": "0", "favorite_count": "24", "author": "KirstenPowers", "is_retweet": true}, {"text": "Ill be on @AC360 coming up discussing breaking news about Russia investigation @cnn", "timestamp": "17:31 - 11. Jan. 2019", "retweet_count": "34", "favorite_count": "540", "author": "KirstenPowers", "is_retweet": true}, {"text": "I\u2019ll be on @TheLeadCNN coming up w two of my faves @SymoneDSanders + @amandacarpenter @CNN", "timestamp": "13:05 - 11. Jan. 2019", "retweet_count": "11", "favorite_count": "303", "author": "KirstenPowers", "is_retweet": true}, {"text": "Keep doing you ", "timestamp": "13:01 - 11. Jan. 2019", "retweet_count": "0", "favorite_count": "19", "author": "KirstenPowers", "is_retweet": true}, {"text": "I\u2019ll be on @AC360 coming up w @David_Gergen talking #govermentshutdown @CNN", "timestamp": "17:02 - 10. Jan. 2019", "retweet_count": "31", "favorite_count": "543", "author": "KirstenPowers", "is_retweet": true}, {"text": "Can\u2019t really \u201clike\u201d this...but thanks for sharing.  Seems crazy but unfortunately believable.", "timestamp": "08:52 - 10. Jan. 2019", "retweet_count": "0", "favorite_count": "18", "author": "KirstenPowers", "is_retweet": true}, {"text": "5/5 \"A Rockefeller Foundation study found that when a company is in crisis, 80 percent of news reports will blame a female CEO \u2014 but if the CEO is a man, only a minority of news reports will blame him.\"  via @joannelipman in @usatoday \n\nGo read the whole column now!", "timestamp": "06:16 - 10. Jan. 2019", "retweet_count": "17", "favorite_count": "78", "author": "KirstenPowers", "is_retweet": true}, {"text": "4) @joannelipman also points out that women are more likely to get the job when a company is in crisis (which CBS is) making success more difficult, and studies show that the media is harder on women CEO's than male when they fail. (So keep your eyes out for this in coverage!)", "timestamp": "06:13 - 10. Jan. 2019", "retweet_count": "17", "favorite_count": "76", "author": "KirstenPowers", "is_retweet": true}, {"text": "3)  In the US, \"more than 70% of Sunday morning politics/policy talk show guests are male. One study of English-language news sites...found that 77 percent of those mentioned in articles are men...women are \u201croutinely marginalized or \u2018symbolically annihilated\u2019 in the news.\u201d", "timestamp": "06:09 - 10. Jan. 2019", "retweet_count": "16", "favorite_count": "62", "author": "KirstenPowers", "is_retweet": true}, {"text": "2) \"Zirinsky, the first woman ever to head up CBS News, is 66 years old. She has been working at the network for 46 years \u2014 which means she started a year before the executive she\u2019s replacing, David Rhodes, was born.\"\n\nHiding in plain sight, apparently.", "timestamp": "06:06 - 10. Jan. 2019", "retweet_count": "27", "favorite_count": "165", "author": "KirstenPowers", "is_retweet": true}, {"text": "1) Please read this important oped by @joannelipman abt the lack of women in influential positions in the media. I will share some key points in this thread. \n\nWhy did it take Susan Zirinsky 46 years to become president of CBS News? https://www.usatoday.com/story/opinion/2019/01/10/news-media-more-women-leaders-susan-zirinsky-cbs-news-president-column/2523913002/ \u2026 @usatoday @usatopinion", "timestamp": "06:03 - 10. Jan. 2019", "retweet_count": "84", "favorite_count": "176", "author": "KirstenPowers", "is_retweet": true}, {"text": "Always love being on with @davidaxelrod. Though we gotta get him on the \u2018gram! #cnn #cnntonight https://www.instagram.com/p/BscK5CXAOiY/?utm_source=ig_twitter_share&igshid=13ahysqi8vep2 \u2026", "timestamp": "20:16 - 9. Jan. 2019", "retweet_count": "4", "favorite_count": "128", "author": "KirstenPowers", "is_retweet": true}, {"text": "Good for u!", "timestamp": "19:34 - 9. Jan. 2019", "retweet_count": "0", "favorite_count": "4", "author": "KirstenPowers", "is_retweet": true}, {"text": "I\u2019ll be on @CNNTonight discussing #GovernmentShutdown with @davidaxelrod #cnn ....coming up", "timestamp": "19:10 - 9. Jan. 2019", "retweet_count": "12", "favorite_count": "268", "author": "KirstenPowers", "is_retweet": true}, {"text": "LOVE THIS.  \n\nI Am (an Older) Woman. Hear Me Roar. \n\nNancy Pelosi, Glenn Close, Susan Zirinsky of CBS: The news has been filled with powerful women over 60.", "timestamp": "17:27 - 9. Jan. 2019", "retweet_count": "69", "favorite_count": "467", "author": "KirstenPowers", "is_retweet": true}, {"text": "You can use our @onepeloton", "timestamp": "21:43 - 7. Jan. 2019", "retweet_count": "0", "favorite_count": "5", "author": "KirstenPowers", "is_retweet": true}, {"text": "Wow", "timestamp": "21:39 - 7. Jan. 2019", "retweet_count": "67", "favorite_count": "418", "author": "KirstenPowers", "is_retweet": true}, {"text": "Yes!!  I think this all the time...they should be given millions of dollars for a start....that\u2019s just a start.", "timestamp": "21:35 - 7. Jan. 2019", "retweet_count": "0", "favorite_count": "5", "author": "KirstenPowers", "is_retweet": true}, {"text": "Awww what a sweet pup!!!", "timestamp": "21:10 - 7. Jan. 2019", "retweet_count": "0", "favorite_count": "0", "author": "KirstenPowers", "is_retweet": true}, {"text": "I\u2019m not your research assistant.  Google it.", "timestamp": "20:50 - 7. Jan. 2019", "retweet_count": "0", "favorite_count": "65", "author": "KirstenPowers", "is_retweet": true}, {"text": "", "timestamp": "20:47 - 7. Jan. 2019", "retweet_count": "0", "favorite_count": "0", "author": "KirstenPowers", "is_retweet": true}, {"text": " @TaraSetmayer is speaking", "timestamp": "20:46 - 7. Jan. 2019", "retweet_count": "67", "favorite_count": "462", "author": "KirstenPowers", "is_retweet": true}, {"text": "Trump should get Mexico to pay for the wall and reopen the government.  Hard working Americans shouldn\u2019t suffer because he can\u2019t fulfill a campaign promise he never should have made. @CNNTonight", "timestamp": "20:30 - 7. Jan. 2019", "retweet_count": "460", "favorite_count": "2442", "author": "KirstenPowers", "is_retweet": true}, {"text": "I\u2019ll be on @CNNTonight coming up #CNN", "timestamp": "19:15 - 7. Jan. 2019", "retweet_count": "6", "favorite_count": "160", "author": "KirstenPowers", "is_retweet": true}, {"text": "Yes that was my understanding... that it was a party w supporters...not something w tv cameras there (like there was when trump said the same word and I assume @DavidRutz was t clutching his pearls.) the video I saw was on a phone...not a tv camera.", "timestamp": "10:00 - 6. Jan. 2019", "retweet_count": "2", "favorite_count": "14", "author": "KirstenPowers", "is_retweet": true}, {"text": "Awesome news!!! ", "timestamp": "18:06 - 4. Jan. 2019", "retweet_count": "2", "favorite_count": "58", "author": "KirstenPowers", "is_retweet": true}, {"text": "I\u2019ll be on @AC360 coming up to discuss Mofo-gate #cnn", "timestamp": "17:49 - 4. Jan. 2019", "retweet_count": "41", "favorite_count": "1113", "author": "KirstenPowers", "is_retweet": true}, {"text": "On l\u2019affaire @RashidaTlaib ...", "timestamp": "13:55 - 4. Jan. 2019", "retweet_count": "526", "favorite_count": "3002", "author": "KirstenPowers", "is_retweet": true}, {"text": "wasn't Black Lives Matter, sorry:", "timestamp": "10:35 - 4. Jan. 2019", "retweet_count": "0", "favorite_count": "0", "author": "KirstenPowers", "is_retweet": true}, {"text": "that was debunked:  https://www.snopes.com/fact-check/black-lives-matter-protesters-chant-for-dead-cops-now-in-baton-rouge/ \u2026", "timestamp": "10:34 - 4. Jan. 2019", "retweet_count": "0", "favorite_count": "3", "author": "KirstenPowers", "is_retweet": true}, {"text": "My point about the collective shrug when Trump said motherf++cker and the freak out when @RashidaTlaib said it isn't that we should have freaked out when Trump said it.  It's that profanity is literally the least of the problems this country faces.", "timestamp": "10:27 - 4. Jan. 2019", "retweet_count": "389", "favorite_count": "2967", "author": "KirstenPowers", "is_retweet": true}, {"text": "Can someone please make #bothsidesism go away.", "timestamp": "10:03 - 4. Jan. 2019", "retweet_count": "28", "favorite_count": "292", "author": "KirstenPowers", "is_retweet": true}, {"text": "4/4 actually one more -- my ultimate point is that the media in covering this needs to not act like it's just a mystery that @RashidaTlaib is being dragged but everyone shrugs when it's Trump.  Don't participate in dragging her for something Trump gets a pass on.", "timestamp": "09:37 - 4. Jan. 2019", "retweet_count": "148", "favorite_count": "856", "author": "KirstenPowers", "is_retweet": true}, {"text": "3/3 Also let's let's not take complaints from the religious right about @RashidaTlaib seriously when they could care less about DJT using the exact same word she used (and more).", "timestamp": "09:35 - 4. Jan. 2019", "retweet_count": "97", "favorite_count": "665", "author": "KirstenPowers", "is_retweet": true}, {"text": "2/ Where were the shrieking headlines when Trump said the same word she used? We need to be clear that there is a major double standard here: white man can curse but if a woman, esp a brown one, esp a Muslim one does it....she will be punished...", "timestamp": "09:30 - 4. Jan. 2019", "retweet_count": "171", "favorite_count": "808", "author": "KirstenPowers", "is_retweet": true}, {"text": "1/Respectfully disagree w/my colleague @CillizzaCNN. He says, \"People don't hold Trump to the same standards that they hold other politicians to.\" Therefore, he argues Tlaib (and thus Dems) will be punished more for her profanity.  But the reason she's treated differently matters", "timestamp": "09:27 - 4. Jan. 2019", "retweet_count": "207", "favorite_count": "775", "author": "KirstenPowers", "is_retweet": true}, {"text": "Do some research. I criticized Obama for immigration more times than i can count.", "timestamp": "08:31 - 4. Jan. 2019", "retweet_count": "6", "favorite_count": "123", "author": "KirstenPowers", "is_retweet": true}, {"text": "Here is DJT saying the word that @RashidaTlaib is being lambasted for saying.", "timestamp": "08:30 - 4. Jan. 2019", "retweet_count": "59", "favorite_count": "168", "author": "KirstenPowers", "is_retweet": true}, {"text": "If @RashidaTlaib saying a curse word offends you, but children being tear gassed at the border, or separated from their parents doesn't, you need to do some soul searching.", "timestamp": "08:22 - 4. Jan. 2019", "retweet_count": "6257", "favorite_count": "25387", "author": "KirstenPowers", "is_retweet": true}, {"text": "", "timestamp": "06:49 - 4. Jan. 2019", "retweet_count": "44", "favorite_count": "417", "author": "KirstenPowers", "is_retweet": true}, {"text": "I\u2019ll be on @AC360 coming up #cnn", "timestamp": "17:04 - 3. Jan. 2019", "retweet_count": "8", "favorite_count": "425", "author": "KirstenPowers", "is_retweet": true}, {"text": "It's never too late to start a business. \n\nA \"50-year-old entrepreneur is nearly twice as likely to have a runaway success as a 30-year-old.\"", "timestamp": "16:19 - 2. Jan. 2019", "retweet_count": "36", "favorite_count": "201", "author": "KirstenPowers", "is_retweet": true}, {"text": "Here we go again. ", "timestamp": "18:54 - 1. Jan. 2019", "retweet_count": "100", "favorite_count": "996", "author": "KirstenPowers", "is_retweet": true}, {"text": "What an inspiring story! It\u2019s #nevertoolate to make new friends \n\nFinding Female Friends Over 50 Can Be Hard. These Women Figured It Out. - The New York Times", "timestamp": "18:49 - 1. Jan. 2019", "retweet_count": "10", "favorite_count": "87", "author": "KirstenPowers", "is_retweet": true}, {"text": "Love this interview with Matthew @emerzian abt his new book \u201cEvery Monday Matters: How to Kick Your Week Off with Passion, Purpose, and Positivity\u201d\n\nAn awesome book to kick of 2019 with!", "timestamp": "18:17 - 1. Jan. 2019", "retweet_count": "6", "favorite_count": "42", "author": "KirstenPowers", "is_retweet": true}, {"text": "Love this thread.  Seems like NC is a recurring theme", "timestamp": "07:45 - 31. Dez. 2018", "retweet_count": "1", "favorite_count": "16", "author": "KirstenPowers", "is_retweet": true}, {"text": "A major lesson I\u2019ve learned in my career is this: Don\u2019t listen to the naysayers and critics bc they are everywhere!\n.\nA Business Insider story today referenced this in a study of 600\u2026 https://www.instagram.com/p/BsBdEW3Accs/?utm_source=ig_twitter_share&igshid=1oic0ilmga1s4 \u2026", "timestamp": "11:44 - 30. Dez. 2018", "retweet_count": "17", "favorite_count": "248", "author": "KirstenPowers", "is_retweet": true}, {"text": "This is sickening.  \n \nGreat reporting by @lauriegnyt \n\n\"He Was a Gay Man on Staff at a Catholic Parish. Then the Threats Began Coming In\"", "timestamp": "09:26 - 29. Dez. 2018", "retweet_count": "25", "favorite_count": "102", "author": "KirstenPowers", "is_retweet": true}, {"text": "Happy Friday! I\u2019ll be on @AC360 coming up #cnn", "timestamp": "16:59 - 28. Dez. 2018", "retweet_count": "10", "favorite_count": "274", "author": "KirstenPowers", "is_retweet": true}, {"text": "Amazing accomplishment!!! One of my favorite books!", "timestamp": "16:43 - 28. Dez. 2018", "retweet_count": "0", "favorite_count": "7", "author": "KirstenPowers", "is_retweet": true}, {"text": "#bestnine 2018 https://www.instagram.com/p/Br83Ahyg9O1/?utm_source=ig_twitter_share&igshid=143gnv60tr9hy \u2026", "timestamp": "16:38 - 28. Dez. 2018", "retweet_count": "1", "favorite_count": "35", "author": "KirstenPowers", "is_retweet": true}, {"text": "Thanks friend!", "timestamp": "08:19 - 28. Dez. 2018", "retweet_count": "0", "favorite_count": "1", "author": "KirstenPowers", "is_retweet": true}, {"text": "Followed u!", "timestamp": "08:19 - 28. Dez. 2018", "retweet_count": "0", "favorite_count": "3", "author": "KirstenPowers", "is_retweet": true}, {"text": "wow this is very advanced!! you will have to lmk how it goes...", "timestamp": "07:42 - 28. Dez. 2018", "retweet_count": "0", "favorite_count": "1", "author": "KirstenPowers", "is_retweet": true}, {"text": "hey i think this might be what i'm looking for but i have some questions...not clear which pages are included in which planner.  is there a way to contact you directly? or just DM me...i followed you. your messages aren't opn.", "timestamp": "07:41 - 28. Dez. 2018", "retweet_count": "0", "favorite_count": "0", "author": "KirstenPowers", "is_retweet": true}, {"text": "this will stay on my desk. and i'm looking for something that will keep me focussed on intentions and goals....so not just a calendar", "timestamp": "07:38 - 28. Dez. 2018", "retweet_count": "0", "favorite_count": "0", "author": "KirstenPowers", "is_retweet": true}, {"text": "Lots of great suggestions in reply to this \u2014 thanks everyone!", "timestamp": "14:06 - 27. Dez. 2018", "retweet_count": "2", "favorite_count": "28", "author": "KirstenPowers", "is_retweet": true}, {"text": "Ok now for the serious stuff:  day planner y/n and if so which one do u like and why?\n\nI\u2019m overwhelmed with the choices.", "timestamp": "13:29 - 27. Dez. 2018", "retweet_count": "18", "favorite_count": "290", "author": "KirstenPowers", "is_retweet": true}, {"text": "\u201cSociologically, the principal difference between white and black evangelicals is that we believe that oppression exists,\u201d \u2066@lisasharper\u2069\n\nAwesome piece by \u2066@elizagriswold\u2069.\n\nEvangelicals of Color Fight Back Against the Religious Right", "timestamp": "10:43 - 27. Dez. 2018", "retweet_count": "49", "favorite_count": "202", "author": "KirstenPowers", "is_retweet": true}, {"text": "", "timestamp": "10:22 - 27. Dez. 2018", "retweet_count": "0", "favorite_count": "0", "author": "KirstenPowers", "is_retweet": true}, {"text": "Go donna!!", "timestamp": "10:21 - 27. Dez. 2018", "retweet_count": "0", "favorite_count": "1", "author": "KirstenPowers", "is_retweet": true}, {"text": "I know! Who knew Twitter could be such a nice place ", "timestamp": "19:24 - 23. Dez. 2018", "retweet_count": "0", "favorite_count": "1", "author": "KirstenPowers", "is_retweet": true}, {"text": "That\u2019s not true\u2014they sound like great majors to me", "timestamp": "19:22 - 23. Dez. 2018", "retweet_count": "0", "favorite_count": "0", "author": "KirstenPowers", "is_retweet": true}, {"text": "This is amazing! ", "timestamp": "17:35 - 23. Dez. 2018", "retweet_count": "22", "favorite_count": "329", "author": "KirstenPowers", "is_retweet": true}, {"text": "Wow. Good for you Kelli!! What an amazing example you are for your son.", "timestamp": "16:30 - 23. Dez. 2018", "retweet_count": "1", "favorite_count": "13", "author": "KirstenPowers", "is_retweet": true}, {"text": "So inspiring ", "timestamp": "16:27 - 23. Dez. 2018", "retweet_count": "15", "favorite_count": "246", "author": "KirstenPowers", "is_retweet": true}, {"text": "Will do", "timestamp": "16:15 - 23. Dez. 2018", "retweet_count": "0", "favorite_count": "0", "author": "KirstenPowers", "is_retweet": true}, {"text": "Thanks for ruining my day", "timestamp": "15:28 - 23. Dez. 2018", "retweet_count": "1", "favorite_count": "87", "author": "KirstenPowers", "is_retweet": true}, {"text": "Haha! I\u2019m actually not thinking of going back to school...I just tweeted out a link to a new book about going to school as an adult to encourage anyone who is thinking of it.", "timestamp": "15:25 - 23. Dez. 2018", "retweet_count": "1", "favorite_count": "44", "author": "KirstenPowers", "is_retweet": true}, {"text": "", "timestamp": "15:19 - 23. Dez. 2018", "retweet_count": "7", "favorite_count": "85", "author": "KirstenPowers", "is_retweet": true}, {"text": "", "timestamp": "15:17 - 23. Dez. 2018", "retweet_count": "2", "favorite_count": "25", "author": "KirstenPowers", "is_retweet": true}, {"text": "Go Nina!", "timestamp": "15:15 - 23. Dez. 2018", "retweet_count": "2", "favorite_count": "27", "author": "KirstenPowers", "is_retweet": true}, {"text": "Don\u2019t give up on your dream! My timeline is full of advice for people who have financial limitations...", "timestamp": "15:12 - 23. Dez. 2018", "retweet_count": "1", "favorite_count": "18", "author": "KirstenPowers", "is_retweet": true}, {"text": "", "timestamp": "14:59 - 23. Dez. 2018", "retweet_count": "8", "favorite_count": "277", "author": "KirstenPowers", "is_retweet": true}, {"text": "Someone else posted this but you weren\u2019t on reply: Start at a community college. http://Fastweb.org  is a site for scholarships. If you go to a 4 year, check with the financial aid office, check for scholarships there. look for a workforce investment act office in your area.", "timestamp": "14:54 - 23. Dez. 2018", "retweet_count": "0", "favorite_count": "19", "author": "KirstenPowers", "is_retweet": true}, {"text": "Go Darlene!", "timestamp": "14:48 - 23. Dez. 2018", "retweet_count": "8", "favorite_count": "143", "author": "KirstenPowers", "is_retweet": true}, {"text": "", "timestamp": "14:41 - 23. Dez. 2018", "retweet_count": "0", "favorite_count": "1", "author": "KirstenPowers", "is_retweet": true}, {"text": "So inspired by you!", "timestamp": "14:38 - 23. Dez. 2018", "retweet_count": "0", "favorite_count": "4", "author": "KirstenPowers", "is_retweet": true}, {"text": "Any advice for Alison from those who went back to school as adults?", "timestamp": "14:37 - 23. Dez. 2018", "retweet_count": "3", "favorite_count": "28", "author": "KirstenPowers", "is_retweet": true}, {"text": "", "timestamp": "14:11 - 23. Dez. 2018", "retweet_count": "0", "favorite_count": "2", "author": "KirstenPowers", "is_retweet": true}, {"text": "Do it!", "timestamp": "14:09 - 23. Dez. 2018", "retweet_count": "0", "favorite_count": "13", "author": "KirstenPowers", "is_retweet": true}, {"text": "Go for it!", "timestamp": "14:09 - 23. Dez. 2018", "retweet_count": "0", "favorite_count": "2", "author": "KirstenPowers", "is_retweet": true}, {"text": "Go julie!", "timestamp": "14:07 - 23. Dez. 2018", "retweet_count": "8", "favorite_count": "176", "author": "KirstenPowers", "is_retweet": true}, {"text": "Monica feeling the never too late vibe too.  She\u2019s right\u2014it\u2019s never too late to change your story.", "timestamp": "13:50 - 23. Dez. 2018", "retweet_count": "16", "favorite_count": "260", "author": "KirstenPowers", "is_retweet": true}, {"text": "", "timestamp": "13:11 - 23. Dez. 2018", "retweet_count": "3", "favorite_count": "90", "author": "KirstenPowers", "is_retweet": true}, {"text": "", "timestamp": "12:55 - 23. Dez. 2018", "retweet_count": "15", "favorite_count": "133", "author": "KirstenPowers", "is_retweet": true}, {"text": "Go for it Belinda!", "timestamp": "12:54 - 23. Dez. 2018", "retweet_count": "0", "favorite_count": "36", "author": "KirstenPowers", "is_retweet": true}, {"text": "", "timestamp": "12:51 - 23. Dez. 2018", "retweet_count": "3", "favorite_count": "67", "author": "KirstenPowers", "is_retweet": true}, {"text": "Love this!!", "timestamp": "12:48 - 23. Dez. 2018", "retweet_count": "32", "favorite_count": "545", "author": "KirstenPowers", "is_retweet": true}, {"text": "That\u2019s ok! Lots of ppl thought that", "timestamp": "12:48 - 23. Dez. 2018", "retweet_count": "0", "favorite_count": "1", "author": "KirstenPowers", "is_retweet": true}, {"text": "Oh I\u2019m not going back to school lol. \n\nJust inspired by people who don\u2019t give up on their dreams. ", "timestamp": "12:26 - 23. Dez. 2018", "retweet_count": "4", "favorite_count": "79", "author": "KirstenPowers", "is_retweet": true}, {"text": "Go for it!", "timestamp": "12:24 - 23. Dez. 2018", "retweet_count": "1", "favorite_count": "39", "author": "KirstenPowers", "is_retweet": true}, {"text": "She baked it a 3:30am lol.  This is amazing", "timestamp": "12:21 - 23. Dez. 2018", "retweet_count": "0", "favorite_count": "7", "author": "KirstenPowers", "is_retweet": true}, {"text": "Love this!", "timestamp": "12:18 - 23. Dez. 2018", "retweet_count": "2", "favorite_count": "71", "author": "KirstenPowers", "is_retweet": true}, {"text": "I\u2019m so inspired by the responses I\u2019m getting about going back to school as an adult... ", "timestamp": "12:17 - 23. Dez. 2018", "retweet_count": "138", "favorite_count": "2114", "author": "KirstenPowers", "is_retweet": true}, {"text": "", "timestamp": "12:15 - 23. Dez. 2018", "retweet_count": "0", "favorite_count": "2", "author": "KirstenPowers", "is_retweet": true}, {"text": "Do it mike!!", "timestamp": "11:39 - 23. Dez. 2018", "retweet_count": "0", "favorite_count": "61", "author": "KirstenPowers", "is_retweet": true}, {"text": "Go mom!! ", "timestamp": "11:38 - 23. Dez. 2018", "retweet_count": "0", "favorite_count": "3", "author": "KirstenPowers", "is_retweet": true}, {"text": "I don\u2019t understand the algorithm ... all I know is once I started \u201cliking\u201d the tweets on ppl I want to see now they usually show up ... don\u2019t know if that helps", "timestamp": "11:36 - 23. Dez. 2018", "retweet_count": "0", "favorite_count": "0", "author": "KirstenPowers", "is_retweet": true}, {"text": "That\u2019s awesome!!", "timestamp": "11:35 - 23. Dez. 2018", "retweet_count": "0", "favorite_count": "6", "author": "KirstenPowers", "is_retweet": true}, {"text": "Go Don! ", "timestamp": "11:33 - 23. Dez. 2018", "retweet_count": "6", "favorite_count": "115", "author": "KirstenPowers", "is_retweet": true}, {"text": "\u2066I have always been a late bloomer and really believe it\u2019s never too late to do anything. \n\nIf you are thinking of going to college as an adult check out this new book by @beecasey\u2069.\n\nIn 'Never Too Late,' Finally, A Guide For Adults Going To College\u201d", "timestamp": "11:05 - 23. Dez. 2018", "retweet_count": "66", "favorite_count": "365", "author": "KirstenPowers", "is_retweet": true}, {"text": "Is it wrong I want pet duck for Christmas?", "timestamp": "10:53 - 23. Dez. 2018", "retweet_count": "82", "favorite_count": "1178", "author": "KirstenPowers", "is_retweet": true}, {"text": "Visiting mom!", "timestamp": "21:35 - 21. Dez. 2018", "retweet_count": "0", "favorite_count": "3", "author": "KirstenPowers", "is_retweet": true}, {"text": "This is disgusting.  And heartbreaking", "timestamp": "21:31 - 21. Dez. 2018", "retweet_count": "40", "favorite_count": "800", "author": "KirstenPowers", "is_retweet": true}, {"text": "I\u2019ll be on @CNNTonight around 10:30pm ET... #cnn", "timestamp": "19:27 - 21. Dez. 2018", "retweet_count": "11", "favorite_count": "316", "author": "KirstenPowers", "is_retweet": true}, {"text": "I care!! That's why I think they system has to be blown up.", "timestamp": "09:11 - 21. Dez. 2018", "retweet_count": "0", "favorite_count": "53", "author": "KirstenPowers", "is_retweet": true}, {"text": "", "timestamp": "09:06 - 21. Dez. 2018", "retweet_count": "0", "favorite_count": "0", "author": "KirstenPowers", "is_retweet": true}, {"text": "FOMO!!", "timestamp": "09:05 - 21. Dez. 2018", "retweet_count": "0", "favorite_count": "3", "author": "KirstenPowers", "is_retweet": true}, {"text": "I'm glad this is over (if it is).  \"Lean In\" focussed too much on telling women how to contort themselves to fit into the system rather than blowing up the system, which is what needs to happen.", "timestamp": "09:00 - 21. Dez. 2018", "retweet_count": "62", "favorite_count": "478", "author": "KirstenPowers", "is_retweet": true}, {"text": "honored to be included in the same sentence with Queen @joanwalsh ", "timestamp": "08:56 - 21. Dez. 2018", "retweet_count": "0", "favorite_count": "2", "author": "KirstenPowers", "is_retweet": true}, {"text": "", "timestamp": "08:51 - 21. Dez. 2018", "retweet_count": "31", "favorite_count": "707", "author": "KirstenPowers", "is_retweet": true}, {"text": "Somehow I just saw this....lol", "timestamp": "19:07 - 20. Dez. 2018", "retweet_count": "67", "favorite_count": "509", "author": "KirstenPowers", "is_retweet": true}, {"text": "Really: why?", "timestamp": "17:49 - 20. Dez. 2018", "retweet_count": "109", "favorite_count": "805", "author": "KirstenPowers", "is_retweet": true}, {"text": "Lol", "timestamp": "17:49 - 20. Dez. 2018", "retweet_count": "0", "favorite_count": "17", "author": "KirstenPowers", "is_retweet": true}, {"text": "I\u2019ll be on @AC360 around 8:30pm ET to discuss Gen. Mattis resignation #cnn", "timestamp": "17:23 - 20. Dez. 2018", "retweet_count": "9", "favorite_count": "253", "author": "KirstenPowers", "is_retweet": true}, {"text": "I\u2019ll be on @AC360 coming up #cnn", "timestamp": "17:36 - 19. Dez. 2018", "retweet_count": "9", "favorite_count": "261", "author": "KirstenPowers", "is_retweet": true}, {"text": "I\u2019ll be on @AC360 coming up to discuss the Flynn news #CNN", "timestamp": "17:01 - 18. Dez. 2018", "retweet_count": "14", "favorite_count": "281", "author": "KirstenPowers", "is_retweet": true}, {"text": "Thank you @miravalresorts for taking such good care of me on my birthday weekend!! Pure heaven and can\u2019t beat this backyard. @ Miraval Resorts https://www.instagram.com/p/BrgvnFGA50P/?utm_source=ig_twitter_share&igshid=zxbegbrv8h2l \u2026", "timestamp": "18:25 - 17. Dez. 2018", "retweet_count": "3", "favorite_count": "145", "author": "KirstenPowers", "is_retweet": true}, {"text": "Congrats!!! ", "timestamp": "14:28 - 15. Dez. 2018", "retweet_count": "0", "favorite_count": "7", "author": "KirstenPowers", "is_retweet": true}, {"text": "", "timestamp": "11:55 - 14. Dez. 2018", "retweet_count": "1", "favorite_count": "20", "author": "KirstenPowers", "is_retweet": true}, {"text": "Thank u friend...love u and hope to see u soon! ", "timestamp": "05:24 - 14. Dez. 2018", "retweet_count": "0", "favorite_count": "35", "author": "KirstenPowers", "is_retweet": true}, {"text": "Lol I love u ", "timestamp": "05:24 - 14. Dez. 2018", "retweet_count": "0", "favorite_count": "6", "author": "KirstenPowers", "is_retweet": true}, {"text": "Yes you don\u2019t need to apologize to any more ppl!!", "timestamp": "20:51 - 12. Dez. 2018", "retweet_count": "0", "favorite_count": "4", "author": "KirstenPowers", "is_retweet": true}, {"text": "Kathy has apologized so everyone pls accept it and move on.  Her intentions were good.", "timestamp": "20:38 - 12. Dez. 2018", "retweet_count": "3", "favorite_count": "136", "author": "KirstenPowers", "is_retweet": true}, {"text": "Kathy I\u2019m in a remote studio bc I\u2019m traveling so the lighting isn\u2019t great ... I\u2019m sure you meant well but as a woman on TV understand I have my looks picked over constantly and it gets tiring", "timestamp": "20:36 - 12. Dez. 2018", "retweet_count": "0", "favorite_count": "2", "author": "KirstenPowers", "is_retweet": true}, {"text": "@PhilippeReines here\u2019s your clip", "timestamp": "19:18 - 12. Dez. 2018", "retweet_count": "3", "favorite_count": "36", "author": "KirstenPowers", "is_retweet": true}, {"text": "From tonight...", "timestamp": "19:18 - 12. Dez. 2018", "retweet_count": "70", "favorite_count": "612", "author": "KirstenPowers", "is_retweet": true}, {"text": "Oh, it happens. You\u2019d be surprised at what complete strangers say to me irl.", "timestamp": "19:16 - 12. Dez. 2018", "retweet_count": "0", "favorite_count": "3", "author": "KirstenPowers", "is_retweet": true}, {"text": "Thanks love ", "timestamp": "19:15 - 12. Dez. 2018", "retweet_count": "0", "favorite_count": "2", "author": "KirstenPowers", "is_retweet": true}, {"text": "Exactly moms *never* lie about those things ", "timestamp": "19:15 - 12. Dez. 2018", "retweet_count": "0", "favorite_count": "1", "author": "KirstenPowers", "is_retweet": true}, {"text": "Listen up! @schemaly is talking...", "timestamp": "19:02 - 12. Dez. 2018", "retweet_count": "11", "favorite_count": "60", "author": "KirstenPowers", "is_retweet": true}, {"text": "", "timestamp": "18:58 - 12. Dez. 2018", "retweet_count": "25", "favorite_count": "222", "author": "KirstenPowers", "is_retweet": true}, {"text": "Why? Who cares?", "timestamp": "18:32 - 12. Dez. 2018", "retweet_count": "0", "favorite_count": "0", "author": "KirstenPowers", "is_retweet": true}, {"text": "I'll be on @AC360 tonight coming up ... tune in! #CNN", "timestamp": "17:20 - 12. Dez. 2018", "retweet_count": "8", "favorite_count": "418", "author": "KirstenPowers", "is_retweet": true}, {"text": "TY!", "timestamp": "13:31 - 12. Dez. 2018", "retweet_count": "4", "favorite_count": "118", "author": "KirstenPowers", "is_retweet": true}, {"text": "I often say \"let me finish\" as an alternative, but many people on my timeline have made this point and i've taken it to heart....I had never thought about it this way. Thanks Twitter peeps!", "timestamp": "13:03 - 12. Dez. 2018", "retweet_count": "105", "favorite_count": "1213", "author": "KirstenPowers", "is_retweet": true}, {"text": "Yes he offered a sincere apology (which I accepted) and said he knows he has a lot to learn in order to be a feminist. That\u2019s all we can expect if each other\u2014 to own our mistakes and try to do better.", "timestamp": "23:11 - 11. Dez. 2018", "retweet_count": "8", "favorite_count": "194", "author": "KirstenPowers", "is_retweet": true}, {"text": "", "timestamp": "23:06 - 11. Dez. 2018", "retweet_count": "76", "favorite_count": "521", "author": "KirstenPowers", "is_retweet": true}, {"text": "It's still a thing! we are working on second season.", "timestamp": "21:11 - 11. Dez. 2018", "retweet_count": "5", "favorite_count": "105", "author": "KirstenPowers", "is_retweet": true}, {"text": "", "timestamp": "19:05 - 11. Dez. 2018", "retweet_count": "0", "favorite_count": "24", "author": "KirstenPowers", "is_retweet": true}, {"text": "Hey sister\u2014I\u2019ll be in touch about the Shrill Bitch Club meeting ... it\u2019s right after the Nasty Woman reunion", "timestamp": "18:59 - 11. Dez. 2018", "retweet_count": "30", "favorite_count": "480", "author": "KirstenPowers", "is_retweet": true}, {"text": "I love this!!!!", "timestamp": "18:55 - 11. Dez. 2018", "retweet_count": "14", "favorite_count": "203", "author": "KirstenPowers", "is_retweet": true}, {"text": "", "timestamp": "18:54 - 11. Dez. 2018", "retweet_count": "2", "favorite_count": "39", "author": "KirstenPowers", "is_retweet": true}, {"text": "Thank you Steve.  Apology accepted. https://twitter.com/stevensutt/status/1072682052250669060 \u2026", "timestamp": "18:51 - 11. Dez. 2018", "retweet_count": "0", "favorite_count": "64", "author": "KirstenPowers", "is_retweet": true}, {"text": "Believe it.", "timestamp": "18:49 - 11. Dez. 2018", "retweet_count": "15", "favorite_count": "188", "author": "KirstenPowers", "is_retweet": true}, {"text": "This is why I make a point to say stop interrupting me or let me finish. Not just because it\u2019s impossible for me to make a point w/out losing my train of thought when someone is talking over me, but also on behalf of all the women who\u2019ve had to put up with this their whole lives.", "timestamp": "18:48 - 11. Dez. 2018", "retweet_count": "210", "favorite_count": "1960", "author": "KirstenPowers", "is_retweet": true}, {"text": "Someone else deal w this please.", "timestamp": "18:45 - 11. Dez. 2018", "retweet_count": "6", "favorite_count": "113", "author": "KirstenPowers", "is_retweet": true}, {"text": "Shrill bitches are welcome here.", "timestamp": "18:38 - 11. Dez. 2018", "retweet_count": "30", "favorite_count": "860", "author": "KirstenPowers", "is_retweet": true}, {"text": "Seriously over the men telling me how to properly respond to being interrupted.", "timestamp": "18:35 - 11. Dez. 2018", "retweet_count": "1256", "favorite_count": "13505", "author": "KirstenPowers", "is_retweet": true}, {"text": "Thank you", "timestamp": "18:31 - 11. Dez. 2018", "retweet_count": "9", "favorite_count": "236", "author": "KirstenPowers", "is_retweet": true}, {"text": "Next time lol", "timestamp": "18:26 - 11. Dez. 2018", "retweet_count": "3", "favorite_count": "96", "author": "KirstenPowers", "is_retweet": true}, {"text": "", "timestamp": "17:57 - 11. Dez. 2018", "retweet_count": "0", "favorite_count": "3", "author": "KirstenPowers", "is_retweet": true}, {"text": "Why indeed. \n\nThe best part was having a GOP operative explain the Democratic Party to me.", "timestamp": "17:57 - 11. Dez. 2018", "retweet_count": "34", "favorite_count": "293", "author": "KirstenPowers", "is_retweet": true}, {"text": "I\u2019ll be up after the break to discuss the lively WH meeting today w @NancyPelosi and @SenSchumer and Trump.  #cnn @AC360", "timestamp": "17:38 - 11. Dez. 2018", "retweet_count": "12", "favorite_count": "252", "author": "KirstenPowers", "is_retweet": true}, {"text": "Thanks Al\u2014I\u2019ll get in my time machine and go back and hide my bra strap which somehow was the most important thing that just happened when I was on @CNNTonight  ", "timestamp": "20:16 - 10. Dez. 2018", "retweet_count": "45", "favorite_count": "1185", "author": "KirstenPowers", "is_retweet": true}, {"text": "Merry Christmas! ", "timestamp": "20:03 - 10. Dez. 2018", "retweet_count": "1", "favorite_count": "56", "author": "KirstenPowers", "is_retweet": true}, {"text": "I\u2019ll on on @CNNTonight coming up ... #CNN", "timestamp": "19:41 - 10. Dez. 2018", "retweet_count": "6", "favorite_count": "183", "author": "KirstenPowers", "is_retweet": true}, {"text": "i like that you use her given name :-)", "timestamp": "11:41 - 9. Dez. 2018", "retweet_count": "0", "favorite_count": "2", "author": "KirstenPowers", "is_retweet": true}, {"text": "God, I love Arizona.  #nofilter https://www.instagram.com/p/BrLYpg_A0tV/?utm_source=ig_twitter_share&igshid=121hb4qxqidl7 \u2026", "timestamp": "11:15 - 9. Dez. 2018", "retweet_count": "4", "favorite_count": "142", "author": "KirstenPowers", "is_retweet": true}, {"text": "this is amazing! i had no idea ducks were so friendly and snuggly....\n\ntime for a pet duck?", "timestamp": "15:57 - 8. Dez. 2018", "retweet_count": "111", "favorite_count": "785", "author": "KirstenPowers", "is_retweet": true}, {"text": "\u201cVery fine people on both sides.\u201d\n\nJames A. Fields Jr. convicted of killing Heather Heyer in Charlottesville car-ramming", "timestamp": "15:22 - 7. Dez. 2018", "retweet_count": "117", "favorite_count": "633", "author": "KirstenPowers", "is_retweet": true}, {"text": "Back atcha ", "timestamp": "10:38 - 6. Dez. 2018", "retweet_count": "0", "favorite_count": "7", "author": "KirstenPowers", "is_retweet": true}, {"text": "You are a Trump supporter so why don\u2019t you condemn his sinful behavior and leave the gay ppl alone?", "timestamp": "10:21 - 6. Dez. 2018", "retweet_count": "46", "favorite_count": "559", "author": "KirstenPowers", "is_retweet": true}, {"text": "Sure why not.", "timestamp": "10:15 - 6. Dez. 2018", "retweet_count": "4", "favorite_count": "155", "author": "KirstenPowers", "is_retweet": true}, {"text": "", "timestamp": "10:11 - 6. Dez. 2018", "retweet_count": "0", "favorite_count": "29", "author": "KirstenPowers", "is_retweet": true}, {"text": "For those who don\u2019t know what I\u2019m referring to re \u2066@Lauren_Daigle\u2069, here is a story abt the \u201ccontroversy\u201d in Christian-land of going on Ellen\u2019s show bc she is gay.  \n\nLauren Daigle Defends Appearing on The Ellen Degeneres Show", "timestamp": "10:09 - 6. Dez. 2018", "retweet_count": "15", "favorite_count": "79", "author": "KirstenPowers", "is_retweet": true}, {"text": "2 Twitter 15:1", "timestamp": "10:02 - 6. Dez. 2018", "retweet_count": "5", "favorite_count": "67", "author": "KirstenPowers", "is_retweet": true}, {"text": "Good Lord people\u2014just leave @Lauren_Daigle alone. \n\nYou can be a faithful Christian and  not condemn homosexuality. \n\nTrue story.", "timestamp": "09:26 - 6. Dez. 2018", "retweet_count": "169", "favorite_count": "2533", "author": "KirstenPowers", "is_retweet": true}, {"text": "God I love this idea! You should maybe add it to your bio/business cards too lol", "timestamp": "08:51 - 6. Dez. 2018", "retweet_count": "0", "favorite_count": "9", "author": "KirstenPowers", "is_retweet": true}, {"text": "love that article -- exactly right -- Ellie is a little watchdog...people are always surprised when i open the door and they see the little furball attached to the fierce bark they heard cc @DraperRobert", "timestamp": "08:31 - 5. Dez. 2018", "retweet_count": "0", "favorite_count": "1", "author": "KirstenPowers", "is_retweet": true}, {"text": "thanks! she is part Lhasa Apso, part Diva lol", "timestamp": "08:30 - 5. Dez. 2018", "retweet_count": "0", "favorite_count": "0", "author": "KirstenPowers", "is_retweet": true}, {"text": "A good reminder that whenever you speak out about racism those who wish to silence you will try to delegitimize you with toxic labels.  \n\nThe new one is to label people calling out white supremacy as \u201cracists.\u201d  Totally Orwellian.", "timestamp": "11:22 - 4. Dez. 2018", "retweet_count": "1", "favorite_count": "90", "author": "KirstenPowers", "is_retweet": true}, {"text": "I just supported @Calabashtea Brookland on @kickstarter to help them give the \u2018communi-tea more love and more healing\u2019! (And more yummy #vegan food)", "timestamp": "14:49 - 3. Dez. 2018", "retweet_count": "1", "favorite_count": "16", "author": "KirstenPowers", "is_retweet": true}, {"text": "Fascinating interview of \u2066@DraperRobert\u2069 on \u2066@nprfreshair\u2069 about his \u2066@NYTmag\u2069 cover story on \u2066@NancyPelosi\u2069\n\nInside Nancy Pelosi's Bid For Speakership : NPR", "timestamp": "13:08 - 3. Dez. 2018", "retweet_count": "0", "favorite_count": "14", "author": "KirstenPowers", "is_retweet": true}, {"text": "", "timestamp": "20:33 - 1. Dez. 2018", "retweet_count": "0", "favorite_count": "6", "author": "KirstenPowers", "is_retweet": true}, {"text": "Out and about. : @woodruffbets https://www.instagram.com/p/Bq3sdY1g0r0/?utm_source=ig_twitter_share&igshid=1wtfidzk45gd6 \u2026", "timestamp": "19:47 - 1. Dez. 2018", "retweet_count": "2", "favorite_count": "95", "author": "KirstenPowers", "is_retweet": true}, {"text": "No a Facebook messenger message", "timestamp": "11:02 - 1. Dez. 2018", "retweet_count": "0", "favorite_count": "4", "author": "KirstenPowers", "is_retweet": true}, {"text": "Fair points.  I\u2019m conflicted abt this.", "timestamp": "06:35 - 1. Dez. 2018", "retweet_count": "13", "favorite_count": "159", "author": "KirstenPowers", "is_retweet": true}, {"text": "Exactly.", "timestamp": "06:25 - 1. Dez. 2018", "retweet_count": "12", "favorite_count": "111", "author": "KirstenPowers", "is_retweet": true}, {"text": "I am and I\u2019ve said that in various interviews and here on Twitter. That doesn\u2019t get posted though does it?", "timestamp": "06:14 - 1. Dez. 2018", "retweet_count": "4", "favorite_count": "104", "author": "KirstenPowers", "is_retweet": true}, {"text": "The piece you wrote is exactly right.  Someone clips something you said, gives it a headline that distorts the actual conversation and then you are threatened and attacked (for me it\u2019s w misogynistic rants) for weeks. \n\nAnd most ppl only read the headline.", "timestamp": "06:10 - 1. Dez. 2018", "retweet_count": "56", "favorite_count": "270", "author": "KirstenPowers", "is_retweet": true}, {"text": "Also sorry for the typos\u2014A reminder to never write tweets without my glasses LOL", "timestamp": "06:00 - 1. Dez. 2018", "retweet_count": "8", "favorite_count": "199", "author": "KirstenPowers", "is_retweet": true}, {"text": "5/5 I don\u2019t see the point in doing what I do for a living if I\u2019m not going to say hard things or try to start hard conversations. I\u2019m not going to do it perfectly and I wont always choose my words perfectly but my intentions are always to raise awareness of issues, not attack ppl", "timestamp": "05:58 - 1. Dez. 2018", "retweet_count": "19", "favorite_count": "294", "author": "KirstenPowers", "is_retweet": true}, {"text": "4). I\u2019m sure there\u2019s plenty of people who would\u2019ve been angry that I was even talking about the fact that racism is an issue but I doubt I would\u2019ve gotten the relentless attacks if Real Clear Politics hadn\u2019t acted so irresponsibility, esp w the click bait headline", "timestamp": "05:53 - 1. Dez. 2018", "retweet_count": "14", "favorite_count": "145", "author": "KirstenPowers", "is_retweet": true}, {"text": "3) If they had posted the entire interview you would\u2019ve seen that I was trying to have a hard conversation about racism and I said quite clearly that all people \u2013 \u2013 including liberals \u2014 need to contend with their own racism and privilege.", "timestamp": "05:51 - 1. Dez. 2018", "retweet_count": "20", "favorite_count": "181", "author": "KirstenPowers", "is_retweet": true}, {"text": "2) posting click-bait to rile up Trump supporters like Real Clear Politics did resulted in two weeks of nonstop attacks just like the one I posted.  That wasn\u2019t an outlier.  Right wing outlets like @FoxNews and @BrietbartNews picked it up and used it to feed the outrage machine", "timestamp": "05:49 - 1. Dez. 2018", "retweet_count": "15", "favorite_count": "174", "author": "KirstenPowers", "is_retweet": true}, {"text": "1) one of the reasons I posted that message was to show what happens when @RealClearNews posts an video of me discussing racism and edits out the part abt me saying that all white ppl need to face up to their racism to make it seem like I only discussed Trump supporters.", "timestamp": "05:45 - 1. Dez. 2018", "retweet_count": "59", "favorite_count": "451", "author": "KirstenPowers", "is_retweet": true}, {"text": "I just deleted the tweet from the woman calling me \u201ccuntbag\u201d etc  and attacking my dogs b/c I didn\u2019t realize when I posted the screenshot her name showed up.\n\nShe is getting attacked and no matter how horrible that message was I have no interest in causing her any harm.", "timestamp": "05:37 - 1. Dez. 2018", "retweet_count": "226", "favorite_count": "4969", "author": "KirstenPowers", "is_retweet": true}, {"text": "", "timestamp": "17:40 - 30. Nov. 2018", "retweet_count": "0", "favorite_count": "1", "author": "KirstenPowers", "is_retweet": true}, {"text": "Its a woman !", "timestamp": "17:15 - 30. Nov. 2018", "retweet_count": "4", "favorite_count": "80", "author": "KirstenPowers", "is_retweet": true}, {"text": "What kid?", "timestamp": "13:02 - 30. Nov. 2018", "retweet_count": "0", "favorite_count": "1", "author": "KirstenPowers", "is_retweet": true}, {"text": "Here it is zoomed in.  Thank god these pol are ok!!! #Anchorage", "timestamp": "10:43 - 30. Nov. 2018", "retweet_count": "108", "favorite_count": "282", "author": "KirstenPowers", "is_retweet": true}, {"text": "Here is a picture a high school friend who lives in Anchorage just sent.", "timestamp": "10:41 - 30. Nov. 2018", "retweet_count": "1057", "favorite_count": "1869", "author": "KirstenPowers", "is_retweet": true}, {"text": "Heard from a friend in Anchorage...she says it was \u201cterrifying\u201d and they are moving to higher ground.", "timestamp": "10:28 - 30. Nov. 2018", "retweet_count": "20", "favorite_count": "177", "author": "KirstenPowers", "is_retweet": true}, {"text": "This is so scary...so many ppl I know in Anchorage.\n\nAlaska earthquake: Tsunami warning in effect - CNN", "timestamp": "10:20 - 30. Nov. 2018", "retweet_count": "32", "favorite_count": "76", "author": "KirstenPowers", "is_retweet": true}, {"text": "Omg. \n\nGrowing up in Alaska we got used to earthquakes but this is beyond what\u2019s normal.", "timestamp": "10:17 - 30. Nov. 2018", "retweet_count": "47", "favorite_count": "221", "author": "KirstenPowers", "is_retweet": true}, {"text": "I am def not an evangelical apologist.  I\u2019m Catholic.", "timestamp": "14:23 - 29. Nov. 2018", "retweet_count": "0", "favorite_count": "6", "author": "KirstenPowers", "is_retweet": true}, {"text": "This pup missed its mommy so much!!  Such a beautiful reunion.", "timestamp": "18:15 - 28. Nov. 2018", "retweet_count": "143", "favorite_count": "986", "author": "KirstenPowers", "is_retweet": true}, {"text": "Awww!", "timestamp": "17:33 - 28. Nov. 2018", "retweet_count": "5", "favorite_count": "133", "author": "KirstenPowers", "is_retweet": true}, {"text": "I\u2019ll be on @AC360 coming up! #cnn", "timestamp": "17:09 - 28. Nov. 2018", "retweet_count": "2", "favorite_count": "181", "author": "KirstenPowers", "is_retweet": true}, {"text": "I seriously had almost no makeup on. I didn\u2019t even have liner under my eyes. \n\nAnd I\u2019ve never heard of a \u201cmore glamour\u201d requirement at CNN", "timestamp": "14:54 - 28. Nov. 2018", "retweet_count": "0", "favorite_count": "8", "author": "KirstenPowers", "is_retweet": true}, {"text": "My hair and makeup is the same today as every other day. Have no idea what you are talking about", "timestamp": "14:16 - 28. Nov. 2018", "retweet_count": "0", "favorite_count": "25", "author": "KirstenPowers", "is_retweet": true}, {"text": "What she said.", "timestamp": "14:10 - 28. Nov. 2018", "retweet_count": "104", "favorite_count": "726", "author": "KirstenPowers", "is_retweet": true}, {"text": "Coming up I\u2019ll be on @TheLeadCNN w all 3 ladies dressed in black.  \n\nRead into it what you will.  \n\n@SymoneDSanders @amandacarpenter", "timestamp": "13:05 - 28. Nov. 2018", "retweet_count": "18", "favorite_count": "506", "author": "KirstenPowers", "is_retweet": true}, {"text": "This is my Ellie\u2019s twin! Is poko a Lhasa or schitzu? @DraperRobert", "timestamp": "20:26 - 27. Nov. 2018", "retweet_count": "0", "favorite_count": "4", "author": "KirstenPowers", "is_retweet": true}, {"text": "There has been an overwhelming response for  \u201cClaiming our Voices\u2014Claiming our Truths\u201d with \u2066@marwilliamson\u2069 at the Washington National Cathedral on Nov 30th.  \n\nA few tix are still available\u2014you don\u2019t want to miss this! \u2066\u2066@WNCathedral\u2069", "timestamp": "18:17 - 27. Nov. 2018", "retweet_count": "9", "favorite_count": "45", "author": "KirstenPowers", "is_retweet": true}, {"text": "You could just unfollow me.", "timestamp": "17:56 - 27. Nov. 2018", "retweet_count": "0", "favorite_count": "12", "author": "KirstenPowers", "is_retweet": true}, {"text": "The cat lobbyists will stop at nothing.", "timestamp": "17:50 - 27. Nov. 2018", "retweet_count": "210", "favorite_count": "2183", "author": "KirstenPowers", "is_retweet": true}, {"text": "This is happening in Iowa.   @ Iowa https://www.instagram.com/p/Bqnho6PgO9qrj3EUNGxRa4yDVapWAY7Soug7S00/?utm_source=ig_twitter_share&igshid=7u9kz3d1akcx \u2026", "timestamp": "12:59 - 25. Nov. 2018", "retweet_count": "5", "favorite_count": "68", "author": "KirstenPowers", "is_retweet": true}, {"text": "I\u2019m sorry\u2014 why exactly do you feel you have the right to tell me what views I\u2019m allowed to express?\n\nDisagree with me, that\u2019s fine, but don\u2019t lecture me about what I\u2019m allowed to say.", "timestamp": "05:49 - 19. Nov. 2018", "retweet_count": "0", "favorite_count": "14", "author": "KirstenPowers", "is_retweet": true}, {"text": "Pelosi has been known to say: \u201cNo one gives you power. You have to take it from them.\u201d \n\nThe leitmotif of her...ascent is that of a woman wresting power away from a male-dominated political machine, until one day the machine discovered she was its master.", "timestamp": "05:41 - 19. Nov. 2018", "retweet_count": "147", "favorite_count": "624", "author": "KirstenPowers", "is_retweet": true}, {"text": "Must Read by my other half @DraperRobert \u2014Nancy Pelosi\u2019s Last Battle https://nyti.ms/2zbQLVZ  @NYTmag", "timestamp": "05:12 - 19. Nov. 2018", "retweet_count": "19", "favorite_count": "82", "author": "KirstenPowers", "is_retweet": true}, {"text": "The last line was \u201cthat includes me\u201d so what are you talking about?", "timestamp": "04:38 - 19. Nov. 2018", "retweet_count": "2", "favorite_count": "122", "author": "KirstenPowers", "is_retweet": true}, {"text": "Is Trump country really better off under Trump? No. It\u2019s falling further behind. - The Washington Post\n\n\u2018The larger the Trump electorate and the larger the degree of Trump support, the worse the county\u2019s economic performance.\u2019", "timestamp": "10:28 - 18. Nov. 2018", "retweet_count": "280", "favorite_count": "641", "author": "KirstenPowers", "is_retweet": true}, {"text": "For those upset abt my comments about racism+Trump supporters, I also said that ALL white ppl (not just Trump supporters) need to examine their own racist assumptions/white privilege that are the result of living in a society that privileges white people. That includes me.", "timestamp": "07:38 - 18. Nov. 2018", "retweet_count": "2618", "favorite_count": "14284", "author": "KirstenPowers", "is_retweet": true}, {"text": "This headline doesn\u2019t capture the whole conversation but the basic point remains: you can\u2019t support a racial demagogue and then claim to not be racist.  \n\nKirsten Powers: Voting For Trump Because You Didnt Like Hillary Clinton \"Doesnt Make You Not Racist\"", "timestamp": "07:28 - 18. Nov. 2018", "retweet_count": "677", "favorite_count": "2733", "author": "KirstenPowers", "is_retweet": true}]