[{"text": "Happiest Birthday Lawrence. How I wish that Allen Ginsberg was here to celebrate with you!", "timestamp": "09:17 - 23. M\u00e4rz 2019", "retweet_count": "0", "favorite_count": "3", "author": "michellekraus", "is_retweet": true}, {"text": "Remembering this wonderful afternoon for climate... https://www.facebook.com/story.php?story_fbid=10217328260855234&id=1134491056 \u2026", "timestamp": "08:02 - 23. M\u00e4rz 2019", "retweet_count": "0", "favorite_count": "0", "author": "michellekraus", "is_retweet": true}, {"text": "Thank you Susan Wolfe for allowing me to cover this for the HuffPo. https://www.facebook.com/story.php?story_fbid=10217328253215043&id=1134491056 \u2026", "timestamp": "08:00 - 23. M\u00e4rz 2019", "retweet_count": "0", "favorite_count": "0", "author": "michellekraus", "is_retweet": true}, {"text": "Here's to many more years Ann!", "timestamp": "07:59 - 23. M\u00e4rz 2019", "retweet_count": "0", "favorite_count": "0", "author": "michellekraus", "is_retweet": true}, {"text": "This is yet another big deal from Governor Gavin. Hooray! Gavin Newsom https://www.facebook.com/politicsgirl/posts/10217322193983566 \u2026", "timestamp": "11:44 - 22. M\u00e4rz 2019", "retweet_count": "0", "favorite_count": "0", "author": "michellekraus", "is_retweet": true}, {"text": "'Man Up' are the most dangerous words in our culture.", "timestamp": "17:34 - 21. M\u00e4rz 2019", "retweet_count": "0", "favorite_count": "0", "author": "michellekraus", "is_retweet": true}, {"text": "Ah those were the days... https://www.facebook.com/politicsgirl/posts/10217317299981219 \u2026", "timestamp": "17:18 - 21. M\u00e4rz 2019", "retweet_count": "0", "favorite_count": "0", "author": "michellekraus", "is_retweet": true}, {"text": "Remembering Allen Ginsberg https://www.facebook.com/politicsgirl/posts/10217317297021145 \u2026", "timestamp": "17:17 - 21. M\u00e4rz 2019", "retweet_count": "0", "favorite_count": "0", "author": "michellekraus", "is_retweet": true}, {"text": "https://www.facebook.com/story.php?story_fbid=10217309076815645&id=1134491056 \u2026", "timestamp": "12:27 - 20. M\u00e4rz 2019", "retweet_count": "0", "favorite_count": "0", "author": "michellekraus", "is_retweet": true}, {"text": "Sometimes the programming on #MadamSecretary is too close to reality. Pray for safey", "timestamp": "16:27 - 19. M\u00e4rz 2019", "retweet_count": "2", "favorite_count": "5", "author": "michellekraus", "is_retweet": true}, {"text": "https://www.facebook.com/politicsgirl/posts/10217302959102706 \u2026", "timestamp": "15:54 - 19. M\u00e4rz 2019", "retweet_count": "0", "favorite_count": "0", "author": "michellekraus", "is_retweet": true}, {"text": "Mark Dawes missing our political dialogues. Hope that you are well. https://www.facebook.com/politicsgirl/posts/10217299814504093 \u2026", "timestamp": "07:16 - 19. M\u00e4rz 2019", "retweet_count": "0", "favorite_count": "0", "author": "michellekraus", "is_retweet": true}, {"text": "One year later, do we feel safe on #FB? https://www.facebook.com/politicsgirl/posts/10217299810543994 \u2026", "timestamp": "07:15 - 19. M\u00e4rz 2019", "retweet_count": "0", "favorite_count": "0", "author": "michellekraus", "is_retweet": true}, {"text": "Important fro the growing number of California renters.", "timestamp": "10:54 - 18. M\u00e4rz 2019", "retweet_count": "0", "favorite_count": "0", "author": "michellekraus", "is_retweet": true}, {"text": "#FB https://www.facebook.com/politicsgirl/videos/262336521371564/ \u2026", "timestamp": "09:42 - 18. M\u00e4rz 2019", "retweet_count": "0", "favorite_count": "0", "author": "michellekraus", "is_retweet": true}, {"text": "'Silence is complicity' -- @JoeBiden on Trump. #WhiteNationalism", "timestamp": "09:49 - 17. M\u00e4rz 2019", "retweet_count": "0", "favorite_count": "0", "author": "michellekraus", "is_retweet": true}, {"text": "'Out out damn spot' -- @Stephanopoulos panel tried to explain away the President's rhetoric and white nationalism. It isn't working folks. @ThisWeekABC", "timestamp": "08:57 - 17. M\u00e4rz 2019", "retweet_count": "0", "favorite_count": "1", "author": "michellekraus", "is_retweet": true}, {"text": "@MickMulvaneyOMB defends the President for his rhetoric and compares him to @MarkZuckerberg for inventing #FB.  @FaceTheNation", "timestamp": "08:36 - 17. M\u00e4rz 2019", "retweet_count": "0", "favorite_count": "0", "author": "michellekraus", "is_retweet": true}, {"text": "you just show up.", "timestamp": "08:29 - 17. M\u00e4rz 2019", "retweet_count": "0", "favorite_count": "0", "author": "michellekraus", "is_retweet": true}, {"text": "While @MeetThePress has Dem candidates galore ... @ChuckTodd", "timestamp": "08:09 - 17. M\u00e4rz 2019", "retweet_count": "0", "favorite_count": "0", "author": "michellekraus", "is_retweet": true}, {"text": "17% increase in hate crimes 2016 to 2017. We must stay vigilant, unify and vote this administration out in 2020. @ThisWeekABC", "timestamp": "08:07 - 17. M\u00e4rz 2019", "retweet_count": "0", "favorite_count": "1", "author": "michellekraus", "is_retweet": true}, {"text": "'Facts that matter @ThisWeek' -- opening for @Stephanopoulos for the Sunday morning political show. Are there facts that don't matter?", "timestamp": "08:04 - 17. M\u00e4rz 2019", "retweet_count": "0", "favorite_count": "0", "author": "michellekraus", "is_retweet": true}, {"text": "#FB this is lovely. Thank you!", "timestamp": "07:27 - 17. M\u00e4rz 2019", "retweet_count": "0", "favorite_count": "0", "author": "michellekraus", "is_retweet": true}, {"text": "Thank you @Judith Droz Keyes for sharing. https://www.facebook.com/story.php?story_fbid=10217282691556030&id=1134491056 \u2026", "timestamp": "18:32 - 16. M\u00e4rz 2019", "retweet_count": "0", "favorite_count": "0", "author": "michellekraus", "is_retweet": true}, {"text": "Century City mall: LAPD respond to report of man with gun", "timestamp": "13:18 - 15. M\u00e4rz 2019", "retweet_count": "0", "favorite_count": "1", "author": "michellekraus", "is_retweet": true}, {"text": "Each year with #RBG is a priviledge and blessing. Happiest Birthday! https://www.facebook.com/politicsgirl/posts/10217272450380007 \u2026", "timestamp": "10:28 - 15. M\u00e4rz 2019", "retweet_count": "0", "favorite_count": "0", "author": "michellekraus", "is_retweet": true}]