[{"text": ". @VinAbrenica to make special appearance during #LGBT gala in #Bukidnon \n\nhttp://www.bukidnononline.com/gala-organized-for-bukidnon-lgbt-community-hunk-celeb-vin-abrenica-to-guest/ \u2026 \n\n@rod_bolivar", "timestamp": "04:13 - 22. M\u00e4rz 2019", "retweet_count": "0", "favorite_count": "2", "author": "mindanaoan", "is_retweet": true}, {"text": "Love you! I know the pain. I am familiar with the pain. Just take it. Let it sink in. Allow it to process. Don't forget you have friends who love you.", "timestamp": "17:00 - 20. M\u00e4rz 2019", "retweet_count": "0", "favorite_count": "1", "author": "mindanaoan", "is_retweet": true}, {"text": "A lot of \"celebrities\" are cashing in on the elections ha. Appearance fees start at Php 200,000 exclusive pa of taxes, airfare, hotel etc.", "timestamp": "18:37 - 15. M\u00e4rz 2019", "retweet_count": "3", "favorite_count": "20", "author": "mindanaoan", "is_retweet": true}]