[{"text": "Scott Walker was finally defeated. But he refuses to go away", "timestamp": "06:42 - 23. M\u00e4rz 2019", "retweet_count": "2", "favorite_count": "4", "author": "Muxywithmoxie", "is_retweet": true}, {"text": "This reminds me, Wisconsinites must have some sort of Cheese Curds Litmus Test for all of the Democratic candidates. It\u2019s a crowded field. We gotta have priorities. #Elections2020 #wipolitics", "timestamp": "18:25 - 17. M\u00e4rz 2019", "retweet_count": "1", "favorite_count": "5", "author": "Muxywithmoxie", "is_retweet": true}]