[{"text": "It took us two hours to \u2018march\u2019 (shuffle) the length of this street and 90 minutes more to send this tweet. I\u2019d say this is at least 2 or 3 times as crowded as the first anti Brexit march I covered as a reporter 2 years ago when the same distance took about half an hour. \u2013 bei Piccadilly Circus", "timestamp": "08:32 - 23. M\u00e4rz 2019", "retweet_count": "6", "favorite_count": "29", "author": "RobertsDan", "is_retweet": true}, {"text": "What was it Rahm Emanuel used to say about a crisis...", "timestamp": "06:12 - 19. M\u00e4rz 2019", "retweet_count": "1", "favorite_count": "4", "author": "RobertsDan", "is_retweet": true}]